bilibili.py
bilibili_api_mcp_server-0.1.3.dist-info/METADATA
bilibili_api_mcp_server-0.1.3.dist-info/WHEEL
bilibili_api_mcp_server-0.1.3.dist-info/entry_points.txt
bilibili_api_mcp_server-0.1.3.dist-info/top_level.txt
bilibili_api_mcp_server-0.1.3.dist-info/RECORD
