Metadata-Version: 2.4
Name: bilibili-api-mcp-server
Version: 0.1.3
Summary: 用于哔哩哔哩 API 的 MCP（模型上下文协议）服务器，支持多种操作
Requires-Python: >=3.12
Requires-Dist: bilibili-api-python>=17.3.0
Requires-Dist: mcp[cli]>=1.12.3
